hathorprocessing/__init__.py
hathorprocessing/allergies.py
hathorprocessing/apache_aps.py
hathorprocessing/apache_patient_result.py
hathorprocessing/apache_pred_var.py
hathorprocessing/care_plan_care_provider.py
hathorprocessing/care_plan_eol.py
hathorprocessing/care_plan_general.py
hathorprocessing/care_plan_goal.py
hathorprocessing/care_plan_infectious_disease.py
hathorprocessing/custom_lab.py
hathorprocessing/diagnosis.py
hathorprocessing/dna.py
hathorprocessing/drugs.py
hathorprocessing/dx.py
hathorprocessing/hospital.py
hathorprocessing/infusion_drug.py
hathorprocessing/intake_output.py
hathorprocessing/lab.py
hathorprocessing/medication.py
hathorprocessing/micro_lab.py
hathorprocessing/note.py
hathorprocessing/nurse_assessment.py
hathorprocessing/nurse_care.py
hathorprocessing/nurse_charting.py
hathorprocessing/past_history.py
hathorprocessing/patient.py
hathorprocessing/physical_exam.py
hathorprocessing/respiratory_care.py
hathorprocessing/respiratory_charting.py
hathorprocessing/treatment.py
hathorprocessing/vital_aperiodic.py
hathorprocessing/vital_periodic.py
hathor_processing-1.2.16.dev0.dist-info/METADATA
hathor_processing-1.2.16.dev0.dist-info/WHEEL
hathor_processing-1.2.16.dev0.dist-info/top_level.txt
hathor_processing-1.2.16.dev0.dist-info/RECORD
