Metadata-Version: 2.1
Name: hathor-processing
Version: 1.2.16.dev0
Summary: UNKNOWN
Home-page: https://github.com/HathorTechnologies/hathor-processing
Author: 
Author-email: 
License: UNKNOWN
Platform: UNKNOWN
Requires-Python: >=3
Requires-Dist: pandas
Requires-Dist: sqlalchemy
